{
	"custId": "",
	"creditCardType": "",
	"cnName": "",
	"enName": "",
	"email": "",
	"mobile": "",
	"currentTelArea": "",
	"currentTel": "",
	"currentPost": "",
	"currentCity": "",
	"currentTown": "",
	"currentAddr": "",
	"education": "",
	"elemSchool": "",
	"birthday": "",
	"compName": "",
	"compPost": "",
	"compCity": "",
	"compTown": "",
	"compAddr": "",
	"compId": "",
	"compTelArea": "",
	"compTel": "",
	"industryType": "",
	"posTitle": "",
	"workYear": "-1",
	"workMonth": "-1",
	"avgSalary": "-1",
	"billMailAddr": "",
	"branchId": "",
	"ebillApply": "",
	"cashRemark": "",
	"channel": ""
}